namesex/__init__.py
namesex/namesex.py
namesex/test_namesex.py
namesex/testdata.py
namesex/data/namesex_data_v2.csv
namesex/data/testdata.csv
namesex/model/logic_light.pickle
namesex/model/namesex_rf.bin
namesex/model/w2v_dictvec_sg_s100i20.pickle
namesex-0.2.5.dist-info/DESCRIPTION.rst
namesex-0.2.5.dist-info/METADATA
namesex-0.2.5.dist-info/RECORD
namesex-0.2.5.dist-info/WHEEL
namesex-0.2.5.dist-info/metadata.json
namesex-0.2.5.dist-info/top_level.txt
