Metadata-Version: 2.0
Name: namesex
Version: 0.2.5
Summary: A gender classifier for Chinese given names
Home-page: https://github.com/hsinmin/namesex
Author: Hsin-Min Lu, Yu-Lun Li, Chi-Yu Lin
Author-email: luim@ntu.edu.tw
License: UNKNOWN
Keywords: classify_sex Chinese_given_name
Platform: UNKNOWN
Classifier: Development Status :: 4 - Beta
Classifier: Intended Audience :: Science/Research
Classifier: Topic :: Scientific/Engineering :: Artificial Intelligence
Classifier: License :: OSI Approved :: GNU General Public License v3 or later (GPLv3+)
Classifier: Programming Language :: Python :: 3
Classifier: Programming Language :: Python :: 3.4
Classifier: Programming Language :: Python :: 3.5
Classifier: Programming Language :: Python :: 3.6
Classifier: Programming Language :: Python :: 3.7
Requires-Dist: numpy
Requires-Dist: scikit-learn (>=0.19.1)
Requires-Dist: scipy
